README.md
setup.cfg
setup.py
vultr.py
vultr_python.egg-info/PKG-INFO
vultr_python.egg-info/SOURCES.txt
vultr_python.egg-info/dependency_links.txt
vultr_python.egg-info/not-zip-safe
vultr_python.egg-info/requires.txt
vultr_python.egg-info/top_level.txt