Metadata-Version: 2.1
Name: vultr-python
Version: 0.1.5
Summary: Python 3 wrapper for the Vultr API v2.0
Home-page: https://github.com/cssnr/vultr-python
Author: Shane
Author-email: shane@sapps.me
License: UNKNOWN
Project-URL: Documentation, https://vultr-python.sapps.me/
Project-URL: Source, https://github.com/cssnr/vultr-python
Platform: any
Classifier: Development Status :: 3 - Alpha
Classifier: Intended Audience :: Developers
Classifier: Intended Audience :: System Administrators
Classifier: Operating System :: OS Independent
Classifier: Programming Language :: Python :: 3 :: Only
Requires-Python: >=3.5
